tools_barebone/__init__.py
tools_barebone/structure_importers/__init__.py
tools_barebone-1.3.0.dist-info/LICENSE.txt
tools_barebone-1.3.0.dist-info/METADATA
tools_barebone-1.3.0.dist-info/WHEEL
tools_barebone-1.3.0.dist-info/top_level.txt
tools_barebone-1.3.0.dist-info/RECORD
