Metadata-Version: 2.1
Name: tools-barebone
Version: 1.3.0
Summary: A base scaffolding to create online web tools
Home-page: http://github.com/materialscloud-org/tools-barebone
Author: Materials Cloud team
License: The MIT license
Download-URL: https://github.com/materialscloud-org/tools-barebone/archive/v1.3.0.tar.gz
Keywords: tool,web tool,Materials Cloud
Platform: UNKNOWN
Classifier: Programming Language :: Python :: 3
Classifier: Programming Language :: Python :: 3.5
Classifier: Programming Language :: Python :: 3.6
Classifier: Programming Language :: Python :: 3.7
Classifier: Programming Language :: Python :: 3.8
Classifier: License :: OSI Approved :: MIT License
Classifier: Operating System :: OS Independent
Classifier: Topic :: Software Development :: Libraries :: Python Modules
Requires-Dist: Flask (>=1)
Requires-Dist: numpy (>=1.16)
Requires-Dist: pyyaml (>=5.3.1)
Requires-Dist: ase (>=3.21.1)
Requires-Dist: qe-tools (>=2.0.0rc2)
Requires-Dist: pymatgen (>=2019.7.2)
Provides-Extra: dev
Requires-Dist: pre-commit (==2.4.0) ; extra == 'dev'
Requires-Dist: pylint (==2.4.4) ; extra == 'dev'
Requires-Dist: prospector (==1.2.0) ; extra == 'dev'
Requires-Dist: pytest (==5.3.5) ; extra == 'dev'
Requires-Dist: pytest-selenium (==2.0.1) ; extra == 'dev'
Requires-Dist: pytest-regressions (==2.0.0) ; extra == 'dev'
